<?xml version="1.0" encoding="UTF-8"?><record_update table="sys_rte_eb_field_mapping">
    <sys_rte_eb_field_mapping action="DELETE">
        <order>100</order>
        <referenced_sys_rte_eb_entity/>
        <source_sys_rte_eb_field display_value="MAC Address">bc104023834152104751e270ceaad3c4</source_sys_rte_eb_field>
        <sys_class_name>sys_rte_eb_field_mapping</sys_class_name>
        <sys_created_by>narendrabekkem</sys_created_by>
        <sys_created_on>2024-10-10 19:06:36</sys_created_on>
        <sys_id>7becb06783c952104751e270ceaad374</sys_id>
        <sys_mod_count>0</sys_mod_count>
        <sys_name/>
        <sys_package display_value="GlobalScopeChagnes" source="bd98deaf9765311081a6bb46f053af78">bd98deaf9765311081a6bb46f053af78</sys_package>
        <sys_policy/>
        <sys_rte_eb_definition display_value="Load Hardware and Related Entries">bffe2af4834152104751e270ceaad325</sys_rte_eb_definition>
        <sys_rte_eb_entity_mapping display_value="tempToNetwork Adapter 2">b7ec706783c952104751e270ceaad3c1</sys_rte_eb_entity_mapping>
        <sys_scope display_value="GlobalScopeChagnes">bd98deaf9765311081a6bb46f053af78</sys_scope>
        <sys_update_name>sys_rte_eb_field_mapping_7becb06783c952104751e270ceaad374</sys_update_name>
        <sys_updated_by>narendrabekkem</sys_updated_by>
        <sys_updated_on>2024-10-10 19:06:36</sys_updated_on>
        <target_sys_rte_eb_field/>
    </sys_rte_eb_field_mapping>
    <sys_update_version action="INSERT_OR_UPDATE">
        <action>DELETE</action>
        <application display_value="GlobalScopeChagnes">bd98deaf9765311081a6bb46f053af78</application>
        <file_path/>
        <instance_id>82a1a4921b26359c9377eb9b2d4bcb78</instance_id>
        <instance_name>dev216183</instance_name>
        <name>sys_rte_eb_field_mapping_7becb06783c952104751e270ceaad374</name>
        <payload><![CDATA[<?xml version="1.0" encoding="UTF-8"?><record_update table="sys_rte_eb_field_mapping"><sys_rte_eb_field_mapping action="INSERT_OR_UPDATE"><order>100</order><referenced_sys_rte_eb_entity/><source_sys_rte_eb_field display_value="MAC Address">bc104023834152104751e270ceaad3c4</source_sys_rte_eb_field><sys_class_name>sys_rte_eb_field_mapping</sys_class_name><sys_created_by>narendrabekkem</sys_created_by><sys_created_on>2024-10-10 19:06:36</sys_created_on><sys_id>7becb06783c952104751e270ceaad374</sys_id><sys_mod_count>0</sys_mod_count><sys_name/><sys_package display_value="GlobalScopeChagnes" source="bd98deaf9765311081a6bb46f053af78">bd98deaf9765311081a6bb46f053af78</sys_package><sys_policy/><sys_rte_eb_definition display_value="Load Hardware and Related Entries">bffe2af4834152104751e270ceaad325</sys_rte_eb_definition><sys_rte_eb_entity_mapping display_value="tempToNetwork Adapter 2">b7ec706783c952104751e270ceaad3c1</sys_rte_eb_entity_mapping><sys_scope display_value="GlobalScopeChagnes">bd98deaf9765311081a6bb46f053af78</sys_scope><sys_update_name>sys_rte_eb_field_mapping_7becb06783c952104751e270ceaad374</sys_update_name><sys_updated_by>narendrabekkem</sys_updated_by><sys_updated_on>2024-10-10 19:06:36</sys_updated_on><target_sys_rte_eb_field/></sys_rte_eb_field_mapping></record_update>]]></payload>
        <payload_hash>1799515508</payload_hash>
        <record_name/>
        <reverted_from/>
        <source>8d63c860472fc2105afe9889316d435f</source>
        <source_table>sys_update_set</source_table>
        <state>previous</state>
        <sys_created_by>narendrabekkem</sys_created_by>
        <sys_created_on>2024-10-10 19:11:54</sys_created_on>
        <sys_id>ed2e382b83c952104751e270ceaad31d</sys_id>
        <sys_mod_count>0</sys_mod_count>
        <sys_recorded_at>19277d8410c0000001</sys_recorded_at>
        <sys_updated_by>narendrabekkem</sys_updated_by>
        <sys_updated_on>2024-10-10 19:11:54</sys_updated_on>
        <type>RTE Field Mapping</type>
        <update_guid>bfecb06757c95210dee6aae93c623075</update_guid>
        <update_guid_history>bfecb06757c95210dee6aae93c623075:-288199858,bfecb06757c95210dee6aae93c623075:-288199858</update_guid_history>
    </sys_update_version>
    <sys_metadata_delete action="INSERT_OR_UPDATE">
        <sys_audit_delete/>
        <sys_class_name>sys_metadata_delete</sys_class_name>
        <sys_created_by>narendrabekkem</sys_created_by>
        <sys_created_on>2024-10-10 19:11:54</sys_created_on>
        <sys_db_object display_value="" name="sys_rte_eb_field_mapping">sys_rte_eb_field_mapping</sys_db_object>
        <sys_id>03caa72718f24668a279de5e7fb0f610</sys_id>
        <sys_metadata>7becb06783c952104751e270ceaad374</sys_metadata>
        <sys_mod_count>0</sys_mod_count>
        <sys_name/>
        <sys_package display_value="GlobalScopeChagnes" source="bd98deaf9765311081a6bb46f053af78">bd98deaf9765311081a6bb46f053af78</sys_package>
        <sys_parent/>
        <sys_policy/>
        <sys_scope display_value="GlobalScopeChagnes">bd98deaf9765311081a6bb46f053af78</sys_scope>
        <sys_scope_delete display_value="">45a9256f5f0647849df15e57985e6ef9</sys_scope_delete>
        <sys_update_name>sys_rte_eb_field_mapping_7becb06783c952104751e270ceaad374</sys_update_name>
        <sys_update_version display_value="sys_rte_eb_field_mapping_7becb06783c952104751e270ceaad374">ed2e382b83c952104751e270ceaad31d</sys_update_version>
        <sys_updated_by>narendrabekkem</sys_updated_by>
        <sys_updated_on>2024-10-10 19:11:54</sys_updated_on>
    </sys_metadata_delete>
</record_update>
